CHANGELOG.txt
LICENSE.txt
MANIFEST.in
README.txt
setup.py
AbSort/__init__.py
AbSort.egg-info/PKG-INFO
AbSort.egg-info/SOURCES.txt
AbSort.egg-info/dependency_links.txt
AbSort.egg-info/top_level.txt