Metadata-Version: 1.1
Name: AbSort
Version: 0.0.1
Summary: A Very Powerful and fully documented package to perform different types of Sorting techniques on the list Data Structure.
Home-page: UNKNOWN
Author: Abenezer Walelign
Author-email: walelignabenezer@gmail.com
License: MIT
Keywords: SortingAlgo
Platform: UNKNOWN
Classifier: Development Status :: 5 - Production/Stable
Classifier: Intended Audience :: Education
Classifier: Operating System :: Microsoft :: Windows :: Windows 10
Classifier: License :: OSI Approved :: MIT License
Classifier: Programming Language :: Python :: 3
